{
  "slug": "quiz-example",
  "title": "Название викторины",
  "published": false,
  "publication_date": "2026-07-18",
  "difficulty": "low",
  "short_description": "Короткое описание для карточки каталога.",
  "intro": "Вступительный текст перед началом прохождения.",
  "cover": "img/covers/example.webp",
  "tags": [
    "animals"
  ],
  "questions": [
    {
      "question": "Какой вариант правильный на изображении?",
      "image": "img/quiz/quiz-example/01.webp",
      "image_alt": "Описание содержимого изображения",
      "answers": [
        {
          "text": "Первый вариант",
          "correct": false,
          "id": "answer-01"
        },
        {
          "text": "Второй вариант",
          "correct": true,
          "id": "answer-02"
        },
        {
          "text": "Третий вариант",
          "correct": false,
          "id": "answer-03"
        },
        {
          "text": "Четвёртый вариант",
          "correct": false,
          "id": "answer-04"
        }
      ],
      "explanation": "Объяснение правильного ответа.",
      "image_source": "Название источника",
      "image_author": "Имя автора",
      "image_source_url": "https://example.com/source",
      "id": "question-01"
    },
    {
      "question": "Вопрос без изображения?",
      "image": "",
      "image_alt": "",
      "answers": [
        {
          "text": "Первый вариант",
          "correct": true,
          "id": "answer-01"
        },
        {
          "text": "Второй вариант",
          "correct": false,
          "id": "answer-02"
        },
        {
          "text": "Третий вариант",
          "correct": false,
          "id": "answer-03"
        },
        {
          "text": "Четвёртый вариант",
          "correct": false,
          "id": "answer-04"
        }
      ],
      "explanation": "Объяснение ответа на вопрос без изображения.",
      "image_source": "",
      "image_author": "",
      "image_source_url": "",
      "id": "question-02"
    }
  ]
}
